aiorwlock/__init__.py
aiorwlock/py.typed
aiorwlock-1.2.0.dist-info/LICENSE
aiorwlock-1.2.0.dist-info/METADATA
aiorwlock-1.2.0.dist-info/WHEEL
aiorwlock-1.2.0.dist-info/top_level.txt
aiorwlock-1.2.0.dist-info/zip-safe
aiorwlock-1.2.0.dist-info/RECORD
