Metadata-Version: 2.1
Name: aiorwlock
Version: 1.2.0
Summary: Read write lock for asyncio.
Home-page: https://github.com/aio-libs/aiorwlock
Author: Nikolay Novik
Author-email: nickolainovik@gmail.com
License: Apache 2
Download-URL: https://pypi.python.org/pypi/aiorwlock
Project-URL: Website, https://github.com/aio-libs/aiorwlock
Project-URL: Issues, https://github.com/aio-libs/aiorwlock/issues
Keywords: aiorwlock,lock,asyncio
Platform: POSIX
Classifier: License :: OSI Approved :: Apache Software License
Classifier: Intended Audience :: Developers
Classifier: Programming Language :: Python :: 3
Classifier: Programming Language :: Python :: 3.6
Classifier: Programming Language :: Python :: 3.7
Classifier: Programming Language :: Python :: 3.8
Classifier: Programming Language :: Python :: 3.9
Classifier: Operating System :: OS Independent
Classifier: Development Status :: 4 - Beta
Classifier: Framework :: AsyncIO
Requires-Python: >=3.6.0
